station_management_mdo_mdi.v

module station_management 
#(
    parameter STATE_IDLE            = 4'd0,
    parameter STATE_PREAMBLE        = 4'd1,
    parameter STATE_START_OF_FRAME  = 4'd2,
    parameter STATE_OPCODE          = 4'd3,
    parameter STATE_PHY_ADDRESS     = 4'd4,
    parameter STATE_REG_ADDRESS     = 4'd5,
    parameter STATE_TURNAROUND      = 4'd6,
    parameter STATE_DATA            = 4'd7,
    parameter STATE_OK              = 4'd8,    
    parameter READ                  = 1'b0,
    parameter WRITE                 = 1'b1
)(
    input   wire reset,
    input   wire clock,
    
    output  wire mdc,
    input   wire mdi,
    output  reg  mdo,
    
    input   wire mode,

    input   wire begin_transaction,
    input   wire [4:0] phy_address,
    input   wire [4:0] reg_address,
    input   wire [15:0] data_in,
    output  reg  [15:0] data_out
);

localparam start_of_frame   = 2'b01;
localparam turnaround       = 2'b10;

reg [3:0] state;
reg [3:0] next_state;

reg [1:0] opcode;
reg [15:0] data_read;

reg [4:0] preamble_counter;
reg       start_of_frame_counter;
reg       opcode_counter;
reg [2:0] phy_address_counter;
reg [2:0] reg_address_counter;
reg       turnaround_counter;
reg [3:0] data_counter;

// MDC
assign mdc = clock;

// State Update
always @(posedge mdc)
    if (reset)
        state <= STATE_IDLE;
    else
        state <= next_state;

// State Machine
always @(*)
    case(state)
        STATE_IDLE:
            if ( begin_transaction )
                next_state <= STATE_PREAMBLE;
            else
                next_state <= STATE_IDLE;
        STATE_PREAMBLE:
            if (preamble_counter == 5'b0)
                next_state <= STATE_START_OF_FRAME;
            else
                next_state <= STATE_PREAMBLE;
        STATE_START_OF_FRAME:
            if (start_of_frame_counter == 0)
                next_state <= STATE_OPCODE;
            else
                next_state <= STATE_START_OF_FRAME;
        STATE_OPCODE:
            if (opcode_counter == 0)
                next_state <= STATE_PHY_ADDRESS;
            else
                next_state <= STATE_OPCODE;
        STATE_PHY_ADDRESS:
            if (phy_address_counter == 0)
                next_state <= STATE_REG_ADDRESS;
            else
                next_state <= STATE_PHY_ADDRESS;
        STATE_REG_ADDRESS:
            if (reg_address_counter == 0)
                next_state <= STATE_TURNAROUND;
            else
                next_state <= STATE_REG_ADDRESS;
        STATE_TURNAROUND:
            if (turnaround_counter == 0)
                next_state <= STATE_DATA;
            else
                next_state <= STATE_TURNAROUND;
        STATE_DATA:
            if (data_counter == 0)
                next_state <= STATE_OK;
            else
                next_state <= STATE_DATA;
        STATE_OK:
            next_state <= STATE_IDLE;
        default:
            next_state <= STATE_IDLE;
    endcase

// State Outputs
always @(*)
    case(state)
        STATE_IDLE:
            mdo <= 0;
        STATE_PREAMBLE:
            mdo <= 1;
        STATE_START_OF_FRAME:
            mdo <= start_of_frame[start_of_frame_counter-:1];
        STATE_OPCODE:
            mdo <= opcode[opcode_counter-:1];
        STATE_PHY_ADDRESS:
            mdo <= phy_address[phy_address_counter-:1];
        STATE_REG_ADDRESS:
            mdo <= reg_address[reg_address_counter-:1];
        STATE_TURNAROUND:
            mdo <= (mode == READ) ? 1'bz : turnaround[turnaround_counter-:1];
        STATE_DATA:
            mdo <= (mode == READ) ? 1'bz : data_in[data_counter-:1];
        default:
            mdo <= 0;
    endcase

always @(posedge mdc)
    if (reset)
        data_read <= 0;
    else if (state == STATE_DATA && mode == READ)
    begin
        $display ("MDI: %b", mdi);
        data_read[data_counter-:1] <= mdi;
    end
    else
        data_read <= 0;

always @(*)
    if (reset)
        data_out <= 0;
    else if (state == STATE_OK)
        data_out <= data_read;
    else
        data_out <= data_out;

always @(*)
    if (mode == READ)
        opcode <= 2'b10;
    else
        opcode <= 2'b01;

// Counters

// Preamble
always @(posedge mdc)
    if (reset)
        preamble_counter <= 5'd31;
    else if (state == STATE_PREAMBLE)
        preamble_counter <= preamble_counter - 1;
    else
        preamble_counter <= 5'd31;

// Start of Frame
always @(posedge mdc)
    if (reset)
        start_of_frame_counter <= 1'b1;
    else if (state == STATE_START_OF_FRAME)
        start_of_frame_counter <= 1'b0;
    else
        start_of_frame_counter <= 1'b1;

// Opcode
always @(posedge mdc)
    if (reset)
        opcode_counter <= 1'b1;
    else if (state == STATE_OPCODE)
        opcode_counter <= 1'b0;
    else
        opcode_counter <= 1'b1;

// PHY Address
always @(posedge mdc)
    if (reset)
        phy_address_counter <= 3'd4;
    else if (state == STATE_PHY_ADDRESS)
        phy_address_counter <= phy_address_counter - 1;
    else
        phy_address_counter <= 3'd4;

// Register Address
always @(posedge mdc)
    if (reset)
        reg_address_counter <= 3'd4;
    else if (state == STATE_REG_ADDRESS)
        reg_address_counter <= reg_address_counter - 1;
    else
        reg_address_counter <= 3'd4;

// Turnaround
always @(posedge mdc)
    if (reset)
        turnaround_counter <= 1'b1;
    else if (state == STATE_TURNAROUND)
        turnaround_counter <= 1'b0;
    else
        turnaround_counter <= 1'b1;

// Data
always @(posedge mdc)
    if (reset)
        data_counter <= 4'd15;
    else if (state == STATE_DATA)
        data_counter <= data_counter - 1;
    else
        data_counter <= 4'd15;

endmodule

station_management_tb.v
module station_management_tb ();

reg reset;
reg clock;

wire mdc;
reg  mdi;
wire mdo;

reg mode;

reg begin_transaction;
reg [4:0] phy_address;
reg [4:0] reg_address;
reg [15:0] data_in;
wire [15:0] data_out;

station_management U_station_management
(
    .reset(reset),
    .clock(clock),
    
    .mdc(mdc),
    .mdi(mdi),
    .mdo(mdo),
    
    .mode(mode),

    .begin_transaction(begin_transaction),
    .phy_address(phy_address),
    .reg_address(reg_address),
    .data_in(data_in),
    .data_out(data_out)
);

integer i;

initial
begin
    $dumpfile("test.vcd");
    $dumpvars(0,station_management_tb);
end

initial
begin
    mdi = 0;
    reset = 1;
    clock = 1;
    mode  = 0;
    begin_transaction = 0;
    phy_address = 5'b00001;
    reg_address = 5'b00010;
    data_in = 16'hFEDC;

    #20 reset = 0;

    #20 begin_transaction = 1;
    #10 begin_transaction = 0;
  
    #490

    for (i=0; i<16; i = i + 1)
    begin
        reading_bit((i%2)? 1'b1 : 1'b0);
    end
    mdi = 0;

    #50

    $finish();
end

always
    #5 clock = ~clock;

task reading_bit;
    input bit;
    begin
        mdi = bit;
        @(posedge mdc);
    end
endtask

task writing_bit;
    begin
        @(posedge mdc);
    end
endtask
endmodule

test.vcd
$date
	Mon May  8 15:40:31 2017
$end
$version
	Icarus Verilog
$end
$timescale
	1s
$end
$scope module station_management_tb $end
$var wire 1 ! mdo $end
$var wire 1 " mdc $end
$var wire 16 # data_out [15:0] $end
$var reg 1 $ begin_transaction $end
$var reg 1 % clock $end
$var reg 16 & data_in [15:0] $end
$var reg 1 ' mdi $end
$var reg 1 ( mode $end
$var reg 5 ) phy_address [4:0] $end
$var reg 5 * reg_address [4:0] $end
$var reg 1 + reset $end
$var integer 32 , i [31:0] $end
$scope module U_station_management $end
$var wire 1 $ begin_transaction $end
$var wire 1 % clock $end
$var wire 16 - data_in [15:0] $end
$var wire 1 " mdc $end
$var wire 1 ' mdi $end
$var wire 1 ( mode $end
$var wire 5 . phy_address [4:0] $end
$var wire 5 / reg_address [4:0] $end
$var wire 1 + reset $end
$var reg 4 0 data_counter [3:0] $end
$var reg 16 1 data_out [15:0] $end
$var reg 16 2 data_read [15:0] $end
$var reg 1 ! mdo $end
$var reg 4 3 next_state [3:0] $end
$var reg 2 4 opcode [1:0] $end
$var reg 1 5 opcode_counter $end
$var reg 3 6 phy_address_counter [2:0] $end
$var reg 5 7 preamble_counter [4:0] $end
$var reg 3 8 reg_address_counter [2:0] $end
$var reg 1 9 start_of_frame_counter $end
$var reg 4 : state [3:0] $end
$var reg 1 ; turnaround_counter $end
$upscope $end
$scope task reading_bit $end
$var reg 1 < bit $end
$upscope $end
$scope task writing_bit $end
$upscope $end
$upscope $end
$enddefinitions $end
#0
$dumpvars
x<
1;
b0 :
19
b100 8
b11111 7
b100 6
15
b10 4
b0 3
b0 2
b0 1
b1111 0
b10 /
b1 .
b1111111011011100 -
bx ,
1+
b10 *
b1 )
0(
0'
b1111111011011100 &
1%
0$
b0 #
1"
0!
$end
#5
0"
0%
#10
1"
1%
#15
0"
0%
#20
1"
1%
0+
#25
0"
0%
#30
1"
1%
#35
0"
0%
#40
b1 3
1"
1%
1$
#45
0"
0%
#50
1!
b1 :
b1 3
1"
1%
0$
#55
0"
0%
#60
b11110 7
1"
1%
#65
0"
0%
#70
b11101 7
1"
1%
#75
0"
0%
#80
b11100 7
1"
1%
#85
0"
0%
#90
b11011 7
1"
1%
#95
0"
0%
#100
b11010 7
1"
1%
#105
0"
0%
#110
b11001 7
1"
1%
#115
0"
0%
#120
b11000 7
1"
1%
#125
0"
0%
#130
b10111 7
1"
1%
#135
0"
0%
#140
b10110 7
1"
1%
#145
0"
0%
#150
b10101 7
1"
1%
#155
0"
0%
#160
b10100 7
1"
1%
#165
0"
0%
#170
b10011 7
1"
1%
#175
0"
0%
#180
b10010 7
1"
1%
#185
0"
0%
#190
b10001 7
1"
1%
#195
0"
0%
#200
b10000 7
1"
1%
#205
0"
0%
#210
b1111 7
1"
1%
#215
0"
0%
#220
b1110 7
1"
1%
#225
0"
0%
#230
b1101 7
1"
1%
#235
0"
0%
#240
b1100 7
1"
1%
#245
0"
0%
#250
b1011 7
1"
1%
#255
0"
0%
#260
b1010 7
1"
1%
#265
0"
0%
#270
b1001 7
1"
1%
#275
0"
0%
#280
b1000 7
1"
1%
#285
0"
0%
#290
b111 7
1"
1%
#295
0"
0%
#300
b110 7
1"
1%
#305
0"
0%
#310
b101 7
1"
1%
#315
0"
0%
#320
b100 7
1"
1%
#325
0"
0%
#330
b11 7
1"
1%
#335
0"
0%
#340
b10 7
1"
1%
#345
0"
0%
#350
b1 7
1"
1%
#355
0"
0%
#360
b10 3
b0 7
1"
1%
#365
0"
0%
#370
0!
b11111 7
b10 :
1"
1%
#375
0"
0%
#380
1!
b11 3
09
1"
1%
#385
0"
0%
#390
b11 :
1"
1%
#395
0"
0%
#400
0!
b100 3
19
05
1"
1%
#405
0"
0%
#410
b100 :
1"
1%
#415
0"
0%
#420
15
b11 6
1"
1%
#425
0"
0%
#430
b10 6
1"
1%
#435
0"
0%
#440
b1 6
1"
1%
#445
0"
0%
#450
1!
b101 3
b0 6
1"
1%
#455
0"
0%
#460
0!
b101 :
b111 6
1"
1%
#465
0"
0%
#470
b11 8
b100 6
1"
1%
#475
0"
0%
#480
b10 8
1"
1%
#485
0"
0%
#490
1!
b1 8
1"
1%
#495
0"
0%
#500
0!
b110 3
b0 8
1"
1%
#505
0"
0%
#510
z!
b111 8
b110 :
1"
1%
#515
0"
0%
#520
b111 3
b100 8
0;
1"
1%
#525
0"
0%
#530
b111 :
1"
1%
#535
0"
0%
#540
1;
b1110 0
1'
1"
1%
1<
b1 ,
#545
0"
0%
#550
b1101 0
b100000000000000 2
0'
0<
b10 ,
1"
1%
#555
0"
0%
#560
b1100 0
1'
1<
b11 ,
1"
1%
#565
0"
0%
#570
b1011 0
b101000000000000 2
0'
0<
b100 ,
1"
1%
#575
0"
0%
#580
b1010 0
1'
1<
b101 ,
1"
1%
#585
0"
0%
#590
b1001 0
b101010000000000 2
0'
0<
b110 ,
1"
1%
#595
0"
0%
#600
b1000 0
1'
1<
b111 ,
1"
1%
#605
0"
0%
#610
b111 0
b101010100000000 2
0'
0<
b1000 ,
1"
1%
#615
0"
0%
#620
b110 0
1'
1<
b1001 ,
1"
1%
#625
0"
0%
#630
b101 0
b101010101000000 2
0'
0<
b1010 ,
1"
1%
#635
0"
0%
#640
b100 0
1'
1<
b1011 ,
1"
1%
#645
0"
0%
#650
b11 0
b101010101010000 2
0'
0<
b1100 ,
1"
1%
#655
0"
0%
#660
b10 0
1'
1<
b1101 ,
1"
1%
#665
0"
0%
#670
b1 0
b101010101010100 2
0'
0<
b1110 ,
1"
1%
#675
0"
0%
#680
b1000 3
b0 0
1'
1<
b1111 ,
1"
1%
#685
0"
0%
#690
b101010101010101 #
b101010101010101 1
0!
b0 3
b1111 0
b101010101010101 2
b1000 :
0'
b10000 ,
1"
1%
#695
0"
0%
#700
b0 :
b0 2
1"
1%
#705
0"
0%
#710
1"
1%
#715
0"
0%
#720
1"
1%
#725
0"
0%
#730
1"
1%
#735
0"
0%
#740
1"
1%
