MAC/rtl/mac/crc/crc.v
`timescale 1ns / 1ps

module crc #(
    parameter POLYNOMIAL    = 5'b00101,
    parameter DATA_WIDTH    = 8,
    parameter CRC_WIDTH     = 5,
    parameter SEED          = 0,
    parameter DEBUG         = 0,
    parameter REVERSE       = 1
)(
    input [DATA_WIDTH-1:0]      data,
    input                       data_enable,
    output reg [CRC_WIDTH-1:0]  crc_out, 
    input                       init,
    input                       clock,
    input                       reset
);

function automatic prev;
    input integer level;
    input integer index;
    input [DATA_WIDTH-1:0]  data;
    input [CRC_WIDTH-1:0]   crc;
    begin
        if (POLYNOMIAL[index])
        begin
            if (level)
            begin
                if (index)
                begin
                    if (DEBUG)
                        $display("LEVEL %0d | crc[%0d] = crc[%0d] ^ crc[%0d] ^ data[%0d]", level, index, (index)?index-1:CRC_WIDTH-1, CRC_WIDTH-1, DATA_WIDTH - 1 - level);                                
                    prev = prev(level-1, (index)?index-1:CRC_WIDTH-1, data, crc) ^ prev(level-1, CRC_WIDTH-1, data, crc) ^ data[DATA_WIDTH-1-level];
                end
                else
                begin
                    if (DEBUG)
                        $display("LEVEL %0d | crc[%0d] = crc[%0d] ^ data[%0d]", level, index, CRC_WIDTH-1, DATA_WIDTH - 1 - level);                                
                    prev = prev(level-1, CRC_WIDTH-1, data, crc) ^ data[DATA_WIDTH-1-level];
                end

            end
            else
            begin
                if (index)
                begin
                    if (DEBUG)
                        $display("LEVEL %0d | crc[%0d] = crc[%0d] ^ crc[%0d] ^ data[%0d] // STOP", level, index, index-1, CRC_WIDTH-1, DATA_WIDTH - 1 - level);                                                
                    prev = crc[index-1-:1] ^ crc[CRC_WIDTH-1-:1] ^ data[DATA_WIDTH-1-level];
                end
                else
                begin
                    if (DEBUG)
                        $display("LEVEL %0d | crc[%0d] = crc[%0d] ^ data[%0d] // STOP", level, index, CRC_WIDTH-1, DATA_WIDTH - 1 - level);                                                
                    prev = crc[CRC_WIDTH-1-:1] ^ data[DATA_WIDTH-1-level];
                end
            end
        end
        else
        begin
            if (level)
            begin
                if (index)
                begin
                    if (DEBUG)
                        $display("LEVEL %0d | crc[%0d] = crc[%0d]", level, index, index - 1);                                                                
                    prev = prev(level-1, index-1, data, crc);
                end
                else
                begin
                    if (DEBUG)
                        $display("LEVEL %0d | crc[%0d] = crc[%0d] ^ data[%0d]", level, index, CRC_WIDTH-1, DATA_WIDTH - 1 - level);                                                                
                    prev = prev(level-1, CRC_WIDTH-1, data, crc) ^ data[DATA_WIDTH-1-level];
                end
            end
            else
            begin
                if (index)
                begin
                    if (DEBUG)
                        $display("LEVEL %0d | crc[%0d] = crc[%0d] // STOP", level, index, index - 1);                                                                                
                    prev = crc[index-1-:1];
                end
                else
                begin
                    if (DEBUG)
                        $display("LEVEL %0d | crc[%0d] = crc[%0d] ^ data[%0d] // STOP", level, index, CRC_WIDTH-1, DATA_WIDTH - 1 - level);                                                                                
                    prev = crc[CRC_WIDTH-1-:1] ^ data[DATA_WIDTH-1-level];
                end
            end
        end
    end
endfunction

wire [DATA_WIDTH-1:0] temp;

genvar j;
generate
if (REVERSE)
begin
    for (j = DATA_WIDTH-1; j >= 0; j = j - 1)
    begin : reverse_loop
        assign temp[DATA_WIDTH-1-j]  = data[j];
    end
end
else
begin
    assign temp = data;
end
endgenerate

genvar i;
generate
for(i = 0; i < CRC_WIDTH; i= i + 1)
begin : loop
    always @(posedge clock)
    begin
        if (reset)
        begin
            crc_out[i+:1] = SEED[i+:1];
        end
        else if (init)
        begin
            crc_out[i+:1] = SEED[i+:1];
        end
        else if (data_enable)
        begin
            if (DEBUG)
                $display("\n\nCRC OUT[%0d]\n***************************************************************************", i); 
            crc_out[i+:1] <= prev(DATA_WIDTH-1,i,temp,crc_out);
        end
    end
end
endgenerate

endmodule

MAC_components/state_machines/rx.v
module rx #(
    parameter       STATE_IDLE          = 3'h0,
    parameter       STATE_PREAMBLE      = 3'h1,
    parameter       STATE_DATA          = 3'h2,
    parameter       STATE_OK            = 3'h3,
    parameter       STATE_DROP          = 3'h4,
    parameter       STATE_ERROR         = 3'h5
)(
    input           reset,
    input           clock,

    input           rx_data_valid,
    input   [7:0]   rx_data,
    input           rx_error,

    output  reg     [7:0]   data_out,
    output  reg             data_out_enable,
    output  reg             data_out_start,
    output  reg             data_out_end,
    input   wire            fifo_full,
    output  reg             error
);

localparam CRC_RESIDUE      = 32'hC704DD7B;
localparam CRC_POLYNOMIAL   = 32'h04C11DB7;
localparam CRC_SEED         = 32'hFFFFFFFF;
localparam MAX_SIZE         = 1518;
localparam MIN_SIZE         = 64;

reg [2:0]  state;
reg [2:0]  next_state;
reg [15:0] frame_length_counter;
reg [15:0] data_counter;
reg        too_long;
reg        too_short;

reg        crc_init;
reg        data_enable;
wire [31:0] crc_out;

reg [39:0] data;

// RX State Machine
always @ (posedge clock)
    if (reset)
        state <= STATE_IDLE;
    else
        state <= next_state;

always @ (*)
    case (state)
        STATE_IDLE:
                if (rx_data_valid && rx_data == 8'h55)
                    next_state = STATE_PREAMBLE;
                else
                    next_state = STATE_IDLE;
        STATE_PREAMBLE:
                if (!rx_data_valid)
                    next_state = STATE_ERROR;
                else if (rx_error)
                    next_state = STATE_DROP;
                else if (rx_data == 8'hd5)
                    next_state = STATE_DATA;
                else if (rx_data == 8'h55)
                    next_state = STATE_PREAMBLE;
                else
                    next_state = STATE_DROP;
        STATE_DATA:
                if (!rx_data_valid && !too_short && !too_long && crc_out == CRC_RESIDUE)
                    next_state = STATE_OK;
                else if ((!rx_data_valid && (too_short || too_long)) || (!rx_data_valid && crc_out != CRC_RESIDUE))
                    next_state = STATE_ERROR;
                else if (fifo_full)
                    next_state = STATE_DROP;
                else if (rx_error || too_long)
                    next_state = STATE_DROP;
                else
                    next_state = STATE_DATA;
        STATE_DROP:
                if (!rx_data_valid)
                    next_state = STATE_ERROR;
                else
                    next_state = STATE_DROP;
        STATE_OK:
                    next_state = STATE_IDLE;
        STATE_ERROR:
                    next_state = STATE_IDLE;
        default:
                    next_state = STATE_IDLE;
    endcase

always @(posedge clock)
    data_out <= data[39-:8];

always @(posedge clock) 
begin
    if (reset)
    begin
        data <= 32'h00000000;
    end
    else if (state == STATE_IDLE)
    begin
        data <= 32'h00000000;
    end
    else
    begin
        data[39-:8] <= data[31-:8];        
        data[31-:8] <= data[23-:8];
        data[23-:8] <= data[15-:8];
        data[15-:8] <= data[7-:8];
        data[7-:8]  <= rx_data;
    end
end

always @ (posedge clock)
    if (reset)
        data_counter <= 0;
    else if (state == STATE_DATA)
        data_counter = data_counter + 1;
    else
        data_counter = 0;

always @ (*)
    if (data_counter > 5 && (state == STATE_DATA || state == STATE_OK || state == STATE_ERROR))
        data_out_enable = 1;
    else
        data_out_enable = 0;

always @(*)
    if (data_counter == 6)
        data_out_start = 1;
    else
        data_out_start = 0;

always @(*)
    if (state == STATE_OK || state == STATE_ERROR)
        data_out_end = 1;
    else
        data_out_end = 0;

always @(*)
    if  (state == STATE_ERROR)
        error = 1;
    else
        error = 0;

// CRC Interface
always @(*)
    if (state == STATE_DATA)
        data_enable = 1;
    else
        data_enable = 0;

always @(*)
    if (state == STATE_PREAMBLE && next_state == STATE_DATA)
        crc_init = 1;
    else
        crc_init = 0;

always @ (posedge clock)
    if (reset)
        frame_length_counter <= 0;
    else if (state == STATE_DATA)
        frame_length_counter = frame_length_counter + 1;
    else
        frame_length_counter = 0;

always @ (*)
    if (frame_length_counter < MIN_SIZE)
        too_short = 1;
    else
        too_short = 0;

always @ (*)
    if (frame_length_counter > MAX_SIZE)
        too_long = 1;
    else
        too_long = 0;

// CRC
crc #(  .POLYNOMIAL(CRC_POLYNOMIAL),
        .DATA_WIDTH(8),
        .CRC_WIDTH(32),
        .SEED(CRC_SEED))
U_crc(
    .reset(reset),
    .clock(clock),
    .init(crc_init),
    .data(rx_data),
    .data_enable(data_enable),
    .crc_out(crc_out)
);

endmodule

MAC_components/state_machines/rx_tb.v
`timescale 1ns / 1ps

module rx_tb();

reg         reset;

wire [7:0]  data_out;
wire        data_out_enable;
wire        data_out_start;
wire        data_out_end;
wire        error;
reg         clock;
reg         rx_data_valid;
reg         rx_error;
reg  [7:0]  rx_data;
reg         fifo_full;
reg  [7:0]  packet [0:1518];   

integer i;

rx U_rx (
    .reset(reset),
    .clock(clock),

    .rx_data_valid(rx_data_valid),
    .rx_data(rx_data),
    .rx_error(rx_error),

    .data_out(data_out),
    .data_out_enable(data_out_enable),
    .data_out_start(data_out_start),
    .data_out_end(data_out_end),
    .fifo_full(fifo_full),
    .error(error)
);

initial
begin
    $dumpfile("test.vcd");
    $dumpvars(0, rx_tb);
end

initial
begin
    reset = 1;  
    clock = 0;        
    rx_data = 0;
    fifo_full = 0;
    $readmemh("packet.hex", packet);

    #15 reset = 0;

    // Send a packet
    for(i = 0; i < 104; i = i + 1)
    begin
        push(packet[i], 1, 0);
    end

    #100

    $finish;
end

always
    #2 clock = ~clock;

task push;
    input [7:0] data;
    input       data_valid;
    input       data_error;
begin
    rx_data = data;
    rx_data_valid = data_valid;
    rx_error = data_error;
    @(posedge clock);
    #1 rx_data_valid = 0;
    rx_error = 0;
    $display("Pushed: %x Valid: %b Error: %b",data, data_valid, data_error );
end
endtask

endmodule

MAC_components/state_machines/test.vcd
$date
	Wed May 10 15:10:21 2017
$end
$version
	Icarus Verilog
$end
$timescale
	1ps
$end
$scope module rx_tb $end
$var wire 1 ! error $end
$var wire 1 " data_out_start $end
$var wire 1 # data_out_end $end
$var wire 1 $ data_out_enable $end
$var wire 8 % data_out [7:0] $end
$var reg 1 & clock $end
$var reg 1 ' fifo_full $end
$var reg 1 ( reset $end
$var reg 8 ) rx_data [7:0] $end
$var reg 1 * rx_data_valid $end
$var reg 1 + rx_error $end
$var integer 32 , i [31:0] $end
$scope module U_rx $end
$var wire 1 & clock $end
$var wire 1 ' fifo_full $end
$var wire 1 ( reset $end
$var wire 8 - rx_data [7:0] $end
$var wire 1 * rx_data_valid $end
$var wire 1 + rx_error $end
$var wire 32 . crc_out [31:0] $end
$var reg 1 / crc_init $end
$var reg 40 0 data [39:0] $end
$var reg 16 1 data_counter [15:0] $end
$var reg 1 2 data_enable $end
$var reg 8 3 data_out [7:0] $end
$var reg 1 $ data_out_enable $end
$var reg 1 # data_out_end $end
$var reg 1 " data_out_start $end
$var reg 1 ! error $end
$var reg 16 4 frame_length_counter [15:0] $end
$var reg 3 5 next_state [2:0] $end
$var reg 3 6 state [2:0] $end
$var reg 1 7 too_long $end
$var reg 1 8 too_short $end
$scope module U_crc $end
$var wire 1 & clock $end
$var wire 8 9 data [7:0] $end
$var wire 1 2 data_enable $end
$var wire 1 / init $end
$var wire 1 ( reset $end
$var wire 8 : temp [7:0] $end
$var reg 32 ; crc_out [31:0] $end
$scope function prev $end
$upscope $end
$scope begin genblk1 $end
$scope begin reverse_loop[0] $end
$upscope $end
$scope begin reverse_loop[1] $end
$upscope $end
$scope begin reverse_loop[2] $end
$upscope $end
$scope begin reverse_loop[3] $end
$upscope $end
$scope begin reverse_loop[4] $end
$upscope $end
$scope begin reverse_loop[5] $end
$upscope $end
$scope begin reverse_loop[6] $end
$upscope $end
$scope begin reverse_loop[7] $end
$upscope $end
$upscope $end
$scope begin loop[0] $end
$upscope $end
$scope begin loop[1] $end
$upscope $end
$scope begin loop[2] $end
$upscope $end
$scope begin loop[3] $end
$upscope $end
$scope begin loop[4] $end
$upscope $end
$scope begin loop[5] $end
$upscope $end
$scope begin loop[6] $end
$upscope $end
$scope begin loop[7] $end
$upscope $end
$scope begin loop[8] $end
$upscope $end
$scope begin loop[9] $end
$upscope $end
$scope begin loop[10] $end
$upscope $end
$scope begin loop[11] $end
$upscope $end
$scope begin loop[12] $end
$upscope $end
$scope begin loop[13] $end
$upscope $end
$scope begin loop[14] $end
$upscope $end
$scope begin loop[15] $end
$upscope $end
$scope begin loop[16] $end
$upscope $end
$scope begin loop[17] $end
$upscope $end
$scope begin loop[18] $end
$upscope $end
$scope begin loop[19] $end
$upscope $end
$scope begin loop[20] $end
$upscope $end
$scope begin loop[21] $end
$upscope $end
$scope begin loop[22] $end
$upscope $end
$scope begin loop[23] $end
$upscope $end
$scope begin loop[24] $end
$upscope $end
$scope begin loop[25] $end
$upscope $end
$scope begin loop[26] $end
$upscope $end
$scope begin loop[27] $end
$upscope $end
$scope begin loop[28] $end
$upscope $end
$scope begin loop[29] $end
$upscope $end
$scope begin loop[30] $end
$upscope $end
$scope begin loop[31] $end
$upscope $end
$upscope $end
$upscope $end
$scope task push $end
$var reg 8 < data [7:0] $end
$var reg 1 = data_error $end
$var reg 1 > data_valid $end
$upscope $end
$upscope $end
$enddefinitions $end
#0
$dumpvars
x>
x=
bx <
bx ;
b0 :
b0 9
x8
x7
bx 6
b0 5
bx 4
bx 3
x2
bx 1
bx 0
0/
bx .
b0 -
bx ,
x+
x*
b0 )
1(
0'
0&
bx %
x$
x#
x"
x!
$end
#2000
02
0!
0#
0"
0$
07
18
b0 6
b0 0
b0 1
b0 4
b11111111111111111111111111111111 .
b11111111111111111111111111111111 ;
1&
#4000
0&
#6000
b0 %
b0 3
1&
#8000
0&
#10000
1&
#12000
0&
#14000
1&
#15000
b10101010 :
b1 5
0+
1*
b1010101 )
b1010101 -
b1010101 9
0=
1>
b1010101 <
b0 ,
0(
#16000
0&
#18000
b1 6
1&
#19000
b1 ,
1*
#20000
0&
#22000
b1010101 0
1&
#23000
b10 ,
1*
#24000
0&
#26000
b101010101010101 0
1&
#27000
b11 ,
1*
#28000
0&
#30000
b10101010101010101010101 0
1&
#31000
b100 ,
1*
#32000
0&
#34000
b1010101010101010101010101010101 0
1&
#35000
b101 ,
1*
#36000
0&
#38000
b101010101010101010101010101010101010101 0
1&
#39000
b110 ,
1*
#40000
0&
#42000
b1010101 %
b1010101 3
1&
#43000
1/
b10101011 :
b10 5
b11010101 )
b11010101 -
b11010101 9
b11010101 <
b111 ,
1*
#44000
0&
#46000
0/
12
b101010101010101010101010101010111010101 0
b10 6
1&
#47000
b11111111 :
b11111111 )
b11111111 -
b11111111 9
b11111111 <
b1000 ,
1*
#48000
0&
#50000
b11111111111111111111111100000000 .
b11111111111111111111111100000000 ;
b101010101010101010101011101010111111111 0
b1 1
b1 4
1&
#51000
b1001 ,
1*
#52000
0&
#54000
b101010101010101110101011111111111111111 0
b11111111111111110000000000000000 .
b11111111111111110000000000000000 ;
b10 4
b10 1
1&
#55000
b1010 ,
1*
#56000
0&
#58000
b11111111000000000000000000000000 .
b11111111000000000000000000000000 ;
b101010111010101111111111111111111111111 0
b11 1
b11 4
1&
#59000
b1011 ,
1*
#60000
0&
#62000
b1101010111111111111111111111111111111111 0
b0 .
b0 ;
b100 4
b100 1
1&
#63000
b1100 ,
1*
#64000
0&
#66000
b10110001111101110100000010110100 .
b10110001111101110100000010110100 ;
b11010101 %
b11010101 3
b1111111111111111111111111111111111111111 0
b101 1
b101 4
1&
#67000
b1101 ,
1*
#68000
0&
#70000
b11111111 %
b11111111 3
b11111111010010000110010001111101 .
b11111111010010000110010001111101 ;
1"
1$
b110 4
b110 1
1&
#71000
b1011 :
b11010000 )
b11010000 -
b11010000 9
b11010000 <
b1110 ,
1*
#72000
0&
#74000
b11010010110110001111011011010101 .
b11010010110110001111011011010101 ;
b1111111111111111111111111111111111010000 0
0"
b111 1
b111 4
1&
#75000
b1010 :
b1010000 )
b1010000 -
b1010000 9
b1010000 <
b1111 ,
1*
#76000
0&
#78000
b1111111111111111111111111101000001010000 0
b11101111011001010111001101010001 .
b11101111011001010111001101010001 ;
b1000 4
b1000 1
1&
#79000
b10011001 :
b10011001 )
b10011001 -
b10011001 9
b10011001 <
b10000 ,
1*
#80000
0&
#82000
b10011111010000010000000101010101 .
b10011111010000010000000101010101 ;
b1111111111111111110100000101000010011001 0
b1001 1
b1001 4
1&
#83000
b11001 :
b10011000 )
b10011000 -
b10011000 9
b10011000 <
b10001 ,
1*
#84000
0&
#86000
b1111111111010000010100001001100110011000 0
b110010100010111111100001011100 .
b110010100010111111100001011100 ;
b1010 4
b1010 1
1&
#87000
b1101001 :
b10010110 )
b10010110 -
b10010110 9
b10010110 <
b10010 ,
1*
#88000
0&
#90000
b11011000001001000011110001100110 .
b11011000001001000011110001100110 ;
b1101000001010000100110011001100010010110 0
b1011 1
b1011 4
1&
#91000
b110001 :
b10001100 )
b10001100 -
b10001100 9
b10001100 <
b10011 ,
1*
#92000
0&
#94000
b101000010011001100110001001011010001100 0
b11010000 %
b11010000 3
b11000011010111001011000001110110 .
b11000011010111001011000001110110 ;
b1100 4
b1100 1
1&
#95000
b10000 :
b1000 )
b1000 -
b1000 9
b1000 <
b10100 ,
1*
#96000
0&
#98000
b1000000011010000001101100110000 .
b1000000011010000001101100110000 ;
b1010000 %
b1010000 3
b1001100110011000100101101000110000001000 0
b1101 1
b1101 4
1&
#99000
b0 :
b0 )
b0 -
b0 9
b0 <
b10101 ,
1*
#100000
0&
#102000
b1001100010010110100011000000100000000000 0
b10011001 %
b10011001 3
b1011100100111010100000001110111 .
b1011100100111010100000001110111 ;
b1110 4
b1110 1
1&
#103000
b10100010 :
b1000101 )
b1000101 -
b1000101 9
b1000101 <
b10110 ,
1*
#104000
0&
#106000
b101000011101100010101000000011 .
b101000011101100010101000000011 ;
b10011000 %
b10011000 3
b1001011010001100000010000000000001000101 0
b1111 1
b1111 4
1&
#107000
b0 :
b0 )
b0 -
b0 9
b0 <
b10111 ,
1*
#108000
0&
#110000
b1000110000001000000000000100010100000000 0
b10010110 %
b10010110 3
b11001000000000010101100001011000 .
b11001000000000010101100001011000 ;
b10000 4
b10000 1
1&
#111000
b11000 ,
1*
#112000
0&
#114000
b1111010110110100010010100100001 .
b1111010110110100010010100100001 ;
b10001100 %
b10001100 3
b100000000000010001010000000000000000 0
b10001 1
b10001 4
1&
#115000
b1110010 :
b1001110 )
b1001110 -
b1001110 9
b1001110 <
b11001 ,
1*
#116000
0&
#118000
b1000101000000000000000001001110 0
b1000 %
b1000 3
b11111100001011011100110010111000 .
b11111100001011011100110010111000 ;
b10010 4
b10010 1
1&
#119000
b1000100 :
b100010 )
b100010 -
b100010 9
b100010 <
b11010 ,
1*
#120000
0&
#122000
b10110110111110101101100011000110 .
b10110110111110101101100011000110 ;
b0 %
b0 3
b100010100000000000000000100111000100010 0
b10011 1
b10011 4
1&
#123000
b10110100 :
b101101 )
b101101 -
b101101 9
b101101 <
b11011 ,
1*
#124000
0&
#126000
b10011100010001000101101 0
b1000101 %
b1000101 3
b11110011010110101111110101101110 .
b11110011010110101111110101101110 ;
b10100 4
b10100 1
1&
#127000
b0 :
b0 )
b0 -
b0 9
b0 <
b11100 ,
1*
#128000
0&
#130000
b11011110000001101011010111010000 .
b11011110000001101011010111010000 ;
b0 %
b0 3
b1001110001000100010110100000000 0
b10101 1
b10101 4
1&
#131000
b11101 ,
1*
#132000
0&
#134000
b100111000100010001011010000000000000000 0
b101011101000000011101111100011 .
b101011101000000011101111100011 ;
b10110 4
b10110 1
1&
#135000
b1 :
b10000000 )
b10000000 -
b10000000 9
b10000000 <
b11110 ,
1*
#136000
0&
#138000
b10111100100101000001100110110 .
b10111100100101000001100110110 ;
b1001110 %
b1001110 3
b10001000101101000000000000000010000000 0
b10111 1
b10111 4
1&
#139000
b10001000 :
b10001 )
b10001 -
b10001 9
b10001 <
b11111 ,
1*
#140000
0&
#142000
b10110100000000000000001000000000010001 0
b100010 %
b100010 3
b10001111110100011011000000100011 .
b10001111110100011011000000100011 ;
b11000 4
b11000 1
1&
#143000
b10101111 :
b11110101 )
b11110101 -
b11110101 9
b11110101 <
b100000 ,
1*
#144000
0&
#146000
b1001001100100111001010111100000 .
b1001001100100111001010111100000 ;
b101101 %
b101101 3
b100000000001000111110101 0
b11001 1
b11001 4
1&
#147000
b10000100 :
b100001 )
b100001 -
b100001 9
b100001 <
b100001 ,
1*
#148000
0&
#150000
b10000000000100011111010100100001 0
b0 %
b0 3
b11111111110100101111011001001010 .
b11111111110100101111011001001010 ;
b11010 4
b11010 1
1&
#151000
b10010101 :
b10101001 )
b10101001 -
b10101001 9
b10101001 <
b100010 ,
1*
#152000
0&
#154000
b1010001110110010101101001000001 .
b1010001110110010101101001000001 ;
b1000000000010001111101010010000110101001 0
b11011 1
b11011 4
1&
#155000
b1111111 :
b11111110 )
b11111110 -
b11111110 9
b11111110 <
b100011 ,
1*
#156000
0&
#158000
b1000111110101001000011010100111111110 0
b10000000 %
b10000000 3
b1111101111101110101011111101010 .
b1111101111101110101011111101010 ;
b11100 4
b11100 1
1&
#159000
b11110011 :
b11001111 )
b11001111 -
b11001111 9
b11001111 <
b100100 ,
1*
#160000
0&
#162000
b10100010110101011010101011100100 .
b10100010110101011010101011100100 ;
b10001 %
b10001 3
b1111010100100001101010011111111011001111 0
b11101 1
b11101 4
1&
#163000
b11001010 :
b1010011 )
b1010011 -
b1010011 9
b1010011 <
b100101 ,
1*
#164000
0&
#166000
b10000110101001111111101100111101010011 0
b11110101 %
b11110101 3
b1011111000001111100111100101111 .
b1011111000001111100111100101111 ;
b11110 4
b11110 1
1&
#167000
b10010101 :
b10101001 )
b10101001 -
b10101001 9
b10101001 <
b100110 ,
1*
#168000
0&
#170000
b1110101110011110110100101001111 .
b1110101110011110110100101001111 ;
b100001 %
b100001 3
b1010100111111110110011110101001110101001 0
b11111 1
b11111 4
1&
#171000
b1111111 :
b11111110 )
b11111110 -
b11111110 9
b11111110 <
b100111 ,
1*
#172000
0&
#174000
b1111111011001111010100111010100111111110 0
b10101001 %
b10101001 3
b11100000111000111001100111010110 .
b11100000111000111001100111010110 ;
b100000 4
b100000 1
1&
#175000
b11111111 :
b11111111 )
b11111111 -
b11111111 9
b11111111 <
b101000 ,
1*
#176000
0&
#178000
b10010111110001111011000011001101 .
b10010111110001111011000011001101 ;
b11111110 %
b11111110 3
b1100111101010011101010011111111011111111 0
b100001 1
b100001 4
1&
#179000
b101001 ,
1*
#180000
0&
#182000
b101001110101001111111101111111111111111 0
b11001111 %
b11001111 3
b1001101000111011110011000101111 .
b1001101000111011110011000101111 ;
b100010 4
b100010 1
1&
#183000
b0 :
b0 )
b0 -
b0 9
b0 <
b101010 ,
1*
#184000
0&
#186000
b11000101011011101100110100100 .
b11000101011011101100110100100 ;
b1010011 %
b1010011 3
b1010100111111110111111111111111100000000 0
b100011 1
b100011 4
1&
#187000
b10010001 :
b10001001 )
b10001001 -
b10001001 9
b10001001 <
b101011 ,
1*
#188000
0&
#190000
b1111111011111111111111110000000010001001 0
b10101001 %
b10101001 3
b11100110000111001011010011100001 .
b11100110000111001011010011100001 ;
b100100 4
b100100 1
1&
#191000
b0 :
b0 )
b0 -
b0 9
b0 <
b101100 ,
1*
#192000
0&
#194000
b11000011100110111000101011001011 .
b11000011100110111000101011001011 ;
b11111110 %
b11111110 3
b1111111111111111000000001000100100000000 0
b100101 1
b100101 4
1&
#195000
b10010001 :
b10001001 )
b10001001 -
b10001001 9
b10001001 <
b101101 ,
1*
#196000
0&
#198000
b1111111100000000100010010000000010001001 0
b11111111 %
b11111111 3
b11101010100111110101101101101001 .
b11101010100111110101101101101001 ;
b100110 4
b100110 1
1&
#199000
b0 :
b0 )
b0 -
b0 9
b0 <
b101110 ,
1*
#200000
0&
#202000
b1110101011110001001100110101111 .
b1110101011110001001100110101111 ;
b10001001000000001000100100000000 0
b100111 1
b100111 4
1&
#203000
b1011100 :
b111010 )
b111010 -
b111010 9
b111010 <
b101111 ,
1*
#204000
0&
#206000
b1000100100000000100010010000000000111010 0
b0 %
b0 3
b11000010011100111110100111101111 .
b11000010011100111110100111101111 ;
b101000 4
b101000 1
1&
#207000
b1011110 :
b1111010 )
b1111010 -
b1111010 9
b1111010 <
b110000 ,
1*
#208000
0&
#210000
b1100011111110000100111111111010 .
b1100011111110000100111111111010 ;
b10001001 %
b10001001 3
b10001001000000000011101001111010 0
b101001 1
b101001 4
1&
#211000
b1010101 :
b10101010 )
b10101010 -
b10101010 9
b10101010 <
b110001 ,
1*
#212000
0&
#214000
b1000100100000000001110100111101010101010 0
b0 %
b0 3
b110110111110111101101000100010 .
b110110111110111101101000100010 ;
b101010 4
b101010 1
1&
#215000
b1101 :
b10110000 )
b10110000 -
b10110000 9
b10110000 <
b110010 ,
1*
#216000
0&
#218000
b100101000111000010011110001 .
b100101000111000010011110001 ;
b10001001 %
b10001001 3
b111010011110101010101010110000 0
b101011 1
b101011 4
1&
#219000
b11010111 :
b11101011 )
b11101011 -
b11101011 9
b11101011 <
b110011 ,
1*
#220000
0&
#222000
b11101001111010101010101011000011101011 0
b0 %
b0 3
b10111111010111001001110000110000 .
b10111111010111001001110000110000 ;
b101100 4
b101100 1
1&
#223000
b10000000 :
b1 )
b1 -
b1 9
b1 <
b110100 ,
1*
#224000
0&
#226000
b10110000111000011110000000101101 .
b10110000111000011110000000101101 ;
b111010 %
b111010 3
b111101010101010101100001110101100000001 0
b101101 1
b101101 4
1&
#227000
b1000 :
b10000 )
b10000 -
b10000 9
b10000 <
b110101 ,
1*
#228000
0&
#230000
b1010101010110000111010110000000100010000 0
b1111010 %
b1111010 3
b1111010110101100100110111000110 .
b1111010110101100100110111000110 ;
b101110 4
b101110 1
1&
#231000
b0 :
b0 )
b0 -
b0 9
b0 <
b110110 ,
1*
#232000
0&
#234000
b11001011100110000110100110001 .
b11001011100110000110100110001 ;
b10101010 %
b10101010 3
b1011000011101011000000010001000000000000 0
b101111 1
b101111 4
1&
#235000
b10000000 :
b1 )
b1 -
b1 9
b1 <
b110111 ,
1*
#236000
0&
#238000
b1110101100000001000100000000000000000001 0
b10110000 %
b10110000 3
b1110100110110011111101010010001 .
b1110100110110011111101010010001 ;
b110000 4
b110000 1
1&
#239000
b0 :
b0 )
b0 -
b0 9
b0 <
b111000 ,
1*
#240000
0&
#242000
b101010010010101111101000111011 .
b101010010010101111101000111011 ;
b11101011 %
b11101011 3
b100010000000000000000000100000000 0
b110001 1
b110001 4
1&
#243000
b111001 ,
1*
#244000
0&
#246000
b1000000000000000000010000000000000000 0
b1 %
b1 3
b11111101010100110101101100110110 .
b11111101010100110101101100110110 ;
b110010 4
b110010 1
1&
#247000
b111010 ,
1*
#248000
0&
#250000
b11101011001011100100110111011010 .
b11101011001011100100110111011010 ;
b10000 %
b10000 3
b1000000000000000000000000 0
b110011 1
b110011 4
1&
#251000
b111011 ,
1*
#252000
0&
#254000
b100000000000000000000000000000000 0
b0 %
b0 3
b11000000101011110011011100011000 .
b11000000101011110011011100011000 ;
b110100 4
b110100 1
1&
#255000
b111100 ,
1*
#256000
0&
#258000
b11110010101111011000100010011001 .
b11110010101111011000100010011001 ;
b1 %
b1 3
b0 0
b110101 1
b110101 4
1&
#259000
b111101 ,
1*
#260000
0&
#262000
b0 %
b0 3
b111101101100100101111101100111 .
b111101101100100101111101100111 ;
b110110 4
b110110 1
1&
#263000
b100 :
b100000 )
b100000 -
b100000 9
b100000 <
b111110 ,
1*
#264000
0&
#266000
b1000100101001001111101010011111 .
b1000100101001001111101010011111 ;
b100000 0
b110111 1
b110111 4
1&
#267000
b10100010 :
b1000101 )
b1000101 -
b1000101 9
b1000101 <
b111111 ,
1*
#268000
0&
#270000
b10000001000101 0
b1111011110101011111010011001011 .
b1111011110101011111010011001011 ;
b111000 4
b111000 1
1&
#271000
b10110010 :
b1001101 )
b1001101 -
b1001101 9
b1001101 <
b1000000 ,
1*
#272000
0&
#274000
b10101010101101111010101110010110 .
b10101010101101111010101110010110 ;
b1000000100010101001101 0
b111001 1
b111001 4
1&
#275000
b10100010 :
b1000101 )
b1000101 -
b1000101 9
b1000101 <
b1000001 ,
1*
#276000
0&
#278000
b100000010001010100110101000101 0
b10010001101000110111101110111000 .
b10010001101000110111101110111000 ;
b111010 4
b111010 1
1&
#279000
b1010010 :
b1001010 )
b1001010 -
b1001010 9
b1001010 <
b1000010 ,
1*
#280000
0&
#282000
b11110011101100100000111001000000 .
b11110011101100100000111001000000 ;
b10000001000101010011010100010101001010 0
b111011 1
b111011 4
1&
#283000
b1100010 :
b1000110 )
b1000110 -
b1000110 9
b1000110 <
b1000011 ,
1*
#284000
0&
#286000
b100010101001101010001010100101001000110 0
b100000 %
b100000 3
b10010011110100100110011000101001 .
b10010011110100100110011000101001 ;
b111100 4
b111100 1
1&
#287000
b11100010 :
b1000111 )
b1000111 -
b1000111 9
b1000111 <
b1000100 ,
1*
#288000
0&
#290000
b110110000100110010100101010000 .
b110110000100110010100101010000 ;
b1000101 %
b1000101 3
b100110101000101010010100100011001000111 0
b111101 1
b111101 4
1&
#291000
b10100010 :
b1000101 )
b1000101 -
b1000101 9
b1000101 <
b1000101 ,
1*
#292000
0&
#294000
b100010101001010010001100100011101000101 0
b1001101 %
b1001101 3
b100101001100000001110101000010 .
b100101001100000001110101000010 ;
b111110 4
b111110 1
1&
#295000
b1100010 :
b1000110 )
b1000110 -
b1000110 9
b1000110 <
b1000110 ,
1*
#296000
0&
#298000
b11010110111000110001001110010 .
b11010110111000110001001110010 ;
b1000101 %
b1000101 3
b100101001000110010001110100010101000110 0
b111111 1
b111111 4
1&
#299000
b11000010 :
b1000011 )
b1000011 -
b1000011 9
b1000011 <
b1000111 ,
1*
#300000
0&
#302000
b100011001000111010001010100011001000011 0
b1001010 %
b1001010 3
b11101011111100011101010001010001 .
b11101011111100011101010001010001 ;
08
b1000000 4
b1000000 1
1&
#303000
b11110010 :
b1001111 )
b1001111 -
b1001111 9
b1001111 <
b1001000 ,
1*
#304000
0&
#306000
b10011111000011000111101001111111 .
b10011111000011000111101001111111 ;
b1000110 %
b1000110 3
b100011101000101010001100100001101001111 0
b1000001 1
b1000001 4
1&
